ldcv.py
ldcv-2.0.3.dist-info/entry_points.txt
ldcv-2.0.3.dist-info/LICENSE
ldcv-2.0.3.dist-info/WHEEL
ldcv-2.0.3.dist-info/METADATA
ldcv-2.0.3.dist-info/RECORD
