Metadata-Version: 2.1
Name: ldcv
Version: 2.0.3
Summary: LangMan Console Version
Home-page: https://github.com/leetking/ldcv
License: GPL-3.0
Author: leetking
Author-email: li_tking@163.com
Requires-Python: >=3.0,<4.0
Classifier: Development Status :: 4 - Beta
Classifier: Environment :: Console
Classifier: Intended Audience :: End Users/Desktop
Classifier: License :: OSI Approved :: GNU General Public License (GPL)
Classifier: License :: OSI Approved :: GNU General Public License v3 (GPLv3)
Classifier: Natural Language :: English
Classifier: Operating System :: POSIX :: Linux
Classifier: Programming Language :: Python :: 3
Classifier: Programming Language :: Python :: 3.3
Classifier: Programming Language :: Python :: 3.4
Classifier: Programming Language :: Python :: 3.5
Classifier: Programming Language :: Python :: 3.6
Classifier: Programming Language :: Python :: 3.7
Classifier: Programming Language :: Python :: 3.8
Classifier: Topic :: Utilities
Requires-Dist: lxml (>=4.2,<5.0)
Project-URL: Repository, https://github.com/leetking/ldcv
